<?xml version="1.0" encoding="UTF-8"?>
<!DOCTYPE plist PUBLIC "-//Apple Computer//DTD PLIST 1.0//EN" "http://www.apple.com/DTDs/PropertyList-1.0.dtd">
<plist version="1.0">
<dict>
	<key>Major Version</key><integer>1</integer>
	<key>Minor Version</key><integer>1</integer>
	<key>Application Version</key><string>8.2.1</string>
	<key>Features</key><integer>5</integer>
	<key>Music Folder</key><string>file://localhost/H:/itunes/</string>
	<key>Library Persistent ID</key><string>C77DA932BD01AA2E</string>
	<key>Tracks</key>
	<dict>
		<key>8152</key>
		<dict>
			<key>Track ID</key><integer>8152</integer>
			<key>Name</key><string>Black Acres</string>
			<key>Artist</key><string>Elysian Fields</string>
			<key>Album</key><string>Queen Of The Meadow</string>
			<key>Kind</key><string>MPEG audio file</string>
			<key>Size</key><integer>4301065</integer>
			<key>Total Time</key><integer>267206</integer>
			<key>Year</key><integer>2000</integer>
			<key>Date Modified</key><date>2005-09-20T13:54:14Z</date>
			<key>Date Added</key><date>2006-11-30T17:50:21Z</date>
			<key>Bit Rate</key><integer>128</integer>
			<key>Sample Rate</key><integer>44100</integer>
			<key>Comments</key><string>www.epitonic.com</string>
			<key>Play Count</key><integer>1</integer>
			<key>Play Date</key><integer>3307997095</integer>
			<key>Play Date UTC</key><date>2008-10-27T23:04:55Z</date>
			<key>Normalization</key><integer>435</integer>
			<key>Artwork Count</key><integer>1</integer>
			<key>Persistent ID</key><string>C77DA932BD01C7B8</string>
			<key>Track Type</key><string>File</string>
			<key>Location</key><string>file://localhost/H:/itunes/Elysian%20Fields/Queen%20Of%20The%20Meadow/Black%20Acres.mp3</string>
			<key>File Folder Count</key><integer>4</integer>
			<key>Library Folder Count</key><integer>1</integer>
		</dict>
		<key>8766</key>
		<dict>
			<key>Track ID</key><integer>8766</integer>
			<key>Name</key><string>Take You On A Cruise</string>
			<key>Artist</key><string>Interpol</string>
			<key>Album</key><string>Antics</string>
			<key>Kind</key><string>MPEG audio file</string>
			<key>Size</key><integer>7075369</integer>
			<key>Total Time</key><integer>294452</integer>
			<key>Track Number</key><integer>4</integer>
			<key>Track Count</key><integer>11</integer>
			<key>Year</key><integer>2004</integer>
			<key>Date Modified</key><date>2005-10-25T11:37:24Z</date>
			<key>Date Added</key><date>2006-11-30T17:50:46Z</date>
			<key>Bit Rate</key><integer>192</integer>
			<key>Sample Rate</key><integer>44100</integer>
			<key>Comments</key><string>Own</string>
			<key>Artwork Count</key><integer>1</integer>
			<key>Persistent ID</key><string>C77DA932BD01CA90</string>
			<key>Track Type</key><string>File</string>
			<key>Location</key><string>file://localhost/H:/itunes/Interpol/Antics/04%20Take%20You%20On%20A%20Cruise.mp3</string>
			<key>File Folder Count</key><integer>4</integer>
			<key>Library Folder Count</key><integer>1</integer>
		</dict>
		<key>10198</key>
		<dict>
			<key>Track ID</key><integer>10198</integer>
			<key>Name</key><string>The Rain Song</string>
			<key>Artist</key><string>Led Zeppelin</string>
			<key>Composer</key><string>Jimmy Page, Robert Plant</string>
			<key>Album</key><string>Houses Of The Holy</string>
			<key>Kind</key><string>MPEG audio file</string>
			<key>Size</key><integer>9355871</integer>
			<key>Total Time</key><integer>459337</integer>
			<key>Disc Number</key><integer>1</integer>
			<key>Disc Count</key><integer>1</integer>
			<key>Track Number</key><integer>2</integer>
			<key>Track Count</key><integer>8</integer>
			<key>Year</key><integer>1973</integer>
			<key>Date Modified</key><date>2005-10-03T09:15:22Z</date>
			<key>Date Added</key><date>2006-11-30T17:51:52Z</date>
			<key>Bit Rate</key><integer>160</integer>
			<key>Sample Rate</key><integer>44100</integer>
			<key>Normalization</key><integer>1477</integer>
			<key>Artwork Count</key><integer>1</integer>
			<key>Sort Name</key><string>Rain Song</string>
			<key>Persistent ID</key><string>C77DA932BD01D0D9</string>
			<key>Track Type</key><string>File</string>
			<key>Location</key><string>file://localhost/H:/itunes/Led%20Zeppelin/Houses%20Of%20The%20Holy/02%20The%20Rain%20Song.mp3</string>
			<key>File Folder Count</key><integer>4</integer>
			<key>Library Folder Count</key><integer>1</integer>
		</dict>
		<key>16688</key>
		<dict>
			<key>Track ID</key><integer>16688</integer>
			<key>Name</key><string>My Names Is Jonas (Live)</string>
			<key>Artist</key><string>Weezer</string>
			<key>Album</key><string>Dusty Gems And Raw Nuggets [Bonus Disc]</string>
			<key>Kind</key><string>MPEG audio file</string>
			<key>Size</key><integer>4415807</integer>
			<key>Total Time</key><integer>219977</integer>
			<key>Disc Number</key><integer>2</integer>
			<key>Disc Count</key><integer>2</integer>
			<key>Track Number</key><integer>5</integer>
			<key>Track Count</key><integer>14</integer>
			<key>Year</key><integer>2004</integer>
			<key>Date Modified</key><date>2005-09-20T13:55:32Z</date>
			<key>Date Added</key><date>2006-11-30T18:05:54Z</date>
			<key>Bit Rate</key><integer>160</integer>
			<key>Sample Rate</key><integer>44100</integer>
			<key>Comments</key><string>burn</string>
			<key>Normalization</key><integer>8945</integer>
			<key>Artwork Count</key><integer>1</integer>
			<key>Persistent ID</key><string>C77DA932BD01ECC4</string>
			<key>Track Type</key><string>File</string>
			<key>Location</key><string>file://localhost/H:/itunes/Weezer/Dusty%20Gems%20And%20Raw%20Nuggets%20%5BBonus%20Disc%5D/2-05%20My%20Names%20Is%20Jonas%20(Live).mp3</string>
			<key>File Folder Count</key><integer>4</integer>
			<key>Library Folder Count</key><integer>1</integer>
		</dict>
		<key>30078</key>
		<dict>
			<key>Track ID</key><integer>30078</integer>
			<key>Name</key><string>Lay Lady Lay</string>
			<key>Artist</key><string>Bob Dylan</string>
			<key>Composer</key><string>Dylan</string>
			<key>Album</key><string>Nashville Skyline</string>
			<key>Genre</key><string>Folk</string>
			<key>Kind</key><string>MPEG audio file</string>
			<key>Size</key><integer>8053164</integer>
			<key>Total Time</key><integer>201273</integer>
			<key>Disc Number</key><integer>1</integer>
			<key>Disc Count</key><integer>1</integer>
			<key>Track Number</key><integer>6</integer>
			<key>Track Count</key><integer>10</integer>
			<key>Year</key><integer>1969</integer>
			<key>Date Modified</key><date>2008-03-18T23:32:45Z</date>
			<key>Date Added</key><date>2008-03-18T22:32:31Z</date>
			<key>Bit Rate</key><integer>320</integer>
			<key>Sample Rate</key><integer>44100</integer>
			<key>Normalization</key><integer>1257</integer>
			<key>Persistent ID</key><string>D5319BBBE6152AE1</string>
			<key>Track Type</key><string>File</string>
			<key>Location</key><string>file://localhost/H:/itunes/Bob%20Dylan/Nashville%20Skyline/06%20Lay%20Lady%20Lay.mp3</string>
			<key>File Folder Count</key><integer>4</integer>
			<key>Library Folder Count</key><integer>1</integer>
		</dict>
	</dict>
	<key>Playlists</key>
	<array>
		<dict>
			<key>Name</key><string>01 January</string>
			<key>Playlist ID</key><integer>67939</integer>
			<key>Playlist Persistent ID</key><string>D5319BBBE6152A78</string>
			<key>Parent Persistent ID</key><string>3152A26BB9C382DF</string>
			<key>All Items</key><true/>
			<key>Playlist Items</key>
			<array>
				<dict>
					<key>Track ID</key><integer>16688</integer>
				</dict>
				<dict>
					<key>Track ID</key><integer>8766</integer>
				</dict>
				<dict>
					<key>Track ID</key><integer>8152</integer>
				</dict>
				<dict>
					<key>Track ID</key><integer>10198</integer>
				</dict>
				<dict>
					<key>Track ID</key><integer>30078</integer>
				</dict>
			</array>
		</dict>
	</array>
</dict>
</plist>
