{
	"name": "December",
	"month": "12",
	"year": "2005",
	"id": "",
	"tracks": [
		{
			"album": {
				"name": "Bewilderness",
				"image": "",
				"id": ""
			},
			"artist": [
				{
					"name": "Bill Bailey",
					"id": ""
				}
			],
			"name": "Unisex Chip Shop",
			"id": "",
			"length": 94902
		},
		{
			"album": {
				"name": "Antics",
				"image": "",
				"id": ""
			},
			"artist": [
				{
					"name": "Interpol",
					"id": ""
				}
			],
			"name": "Boxer",
			"id": "",
			"length": 152894
		},
		{
			"album": {
				"name": "Anthology",
				"image": "",
				"year": 1998,
				"id": ""
			},
			"artist": [
				{
					"name": "John Lennon",
					"id": ""
				}
			],
			"name": "Look At Me",
			"id": "",
			"length": 172721
		},
		{
			"album": {
				"name": "American Recordings",
				"image": "",
				"year": 1994,
				"id": ""
			},
			"artist": [
				{
					"name": "Johnny Cash",
					"id": "6kACVPfCOnqzgfEF5ryl0x"
				}
			],
			"name": "The Man Who Couldn't Cry",
			"id": "",
			"length": 301486
		},
		{
			"album": {
				"name": "Heart And Soul",
				"image": "",
				"year": 1980,
				"id": ""
			},
			"artist": [
				{
					"name": "Joy Division",
					"id": ""
				}
			],
			"name": "Atmosphere",
			"id": "",
			"length": 251062
		}
	]
}