{
	"name": "January Top 5 2010",
	"month": {
		"label": "january",
		"value": 1
	},
	"year": "2010",
	"id": "0Lli0TKJiIeZouiH0CFTw0",
	"tracks": [
		{
			"album": {
				"name": "Heligoland",
				"year": "",
				"id": "4e3b22ec-305e-44dc-85a9-e94b8abd95a5",
				"externalId": {
					"spotify": null
				}
			},
			"artists": [
				{
					"name": "Massive Attack",
					"id": "5872c080-2650-4417-a57c-f928e22d7944",
					"externalId": {
						"spotify": null
					}
				}
			],
			"name": "Paradise Circus",
			"id": "8dc4c7eb-71af-43fd-9273-ca52650dc060",
			"length": 313000,
			"externalId": {
				"spotify": null
			}
		},
		{
			"album": {
				"name": "Babylon By Car",
				"year": "",
				"id": "0edd7c07-167e-4f92-9550-070307cedb4d",
				"externalId": {
					"spotify": null
				}
			},
			"artists": [
				{
					"name": "Bot'Ox",
					"id": "2b00dc08-98ce-4d90-b12b-c0d566ecc6ca",
					"externalId": {
						"spotify": null
					}
				}
			],
			"name": "Blue Steel",
			"id": "64ab74c6-d9ee-479a-832e-6f921e9f3e30",
			"length": 197000,
			"externalId": {
				"spotify": null
			}
		},
		{
			"album": {
				"name": "Unmap",
				"year": "",
				"id": "1ceef098-99cb-4ff5-8451-7da315ffeeed",
				"externalId": {
					"spotify": null
				}
			},
			"artists": [
				{
					"name": "Volcano Choir",
					"id": "14929caf-5e1a-450e-9ceb-510c27916738",
					"externalId": {
						"spotify": null
					}
				}
			],
			"name": "Island, IS",
			"id": "457d57b1-cd92-4c73-821a-7ed4a7b68cc2",
			"length": 248000,
			"externalId": {
				"spotify": null
			}
		},
		{
			"album": {
				"name": "Tons Of Friends",
				"year": "",
				"id": "758de262-cf65-46bb-99b2-0a88d52bc6aa",
				"externalId": {
					"spotify": null
				}
			},
			"artists": [
				{
					"name": "Crookers",
					"id": "4cde558a-2418-4f04-a03d-36a3ea666900",
					"externalId": {
						"spotify": null
					}
				},
				{
					"name": "KiD CuDi",
					"id": "fce30177-acc9-40b7-b0a1-0195ba5e4d6e",
					"externalId": {
						"spotify": null
					}
				}
			],
			"name": "Embrace The Martian",
			"id": "1080a807-3a02-41e8-b397-f2c6dcf19aec",
			"length": 217000,
			"externalId": {
				"spotify": null
			}
		},
		{
			"album": {
				"name": "One Life Stand",
				"year": "",
				"id": "9f59002d-192a-43c3-9f7b-5e84bd308e53",
				"externalId": {
					"spotify": null
				}
			},
			"artists": [
				{
					"name": "Hot Chip",
					"id": "f2bfcbb3-8365-4c53-851c-e0d555a55f89",
					"externalId": {
						"spotify": null
					}
				}
			],
			"name": "One Life Stand",
			"id": "39c630d8-6409-446d-8209-f124d58f5783",
			"length": 324000,
			"externalId": {
				"spotify": null
			}
		}
	]
}