﻿[{"href":"https://api.spotify.com/v1/playlists/0nZHrd2fme3Bvc8epP2QrL/tracks?offset=0&limit=100","items":[{"added_at":"2016-04-27T14:52:47Z","added_by":{"external_urls":{"spotify":"https://open.spotify.com/user/1162685727"},"href":"https://api.spotify.com/v1/users/1162685727","id":"1162685727","type":"user","uri":"spotify:user:1162685727"},"is_local":false,"primary_color":null,"track":{"album":{"album_type":"single","artists":[{"external_urls":{"spotify":"https://open.spotify.com/artist/1QAJqy2dA3ihHBFIHRphZj"},"href":"https://api.spotify.com/v1/artists/1QAJqy2dA3ihHBFIHRphZj","id":"1QAJqy2dA3ihHBFIHRphZj","name":"Cigarettes After Sex","type":"artist","uri":"spotify:artist:1QAJqy2dA3ihHBFIHRphZj"}],"available_markets":[],"external_urls":{"spotify":"https://open.spotify.com/album/5GvLhLPpP03FuLvxgdEnpj"},"href":"https://api.spotify.com/v1/albums/5GvLhLPpP03FuLvxgdEnpj","id":"5GvLhLPpP03FuLvxgdEnpj","images":[{"height":640,"url":"https://i.scdn.co/image/ab67616d0000b27329a9946d5f7bb3aa9da8853d","width":640},{"height":300,"url":"https://i.scdn.co/image/ab67616d00001e0229a9946d5f7bb3aa9da8853d","width":300},{"height":64,"url":"https://i.scdn.co/image/ab67616d0000485129a9946d5f7bb3aa9da8853d","width":64}],"name":"I.","release_date":"2012-07-21","release_date_precision":"day","total_tracks":4,"type":"album","uri":"spotify:album:5GvLhLPpP03FuLvxgdEnpj"},"artists":[{"external_urls":{"spotify":"https://open.spotify.com/artist/1QAJqy2dA3ihHBFIHRphZj"},"href":"https://api.spotify.com/v1/artists/1QAJqy2dA3ihHBFIHRphZj","id":"1QAJqy2dA3ihHBFIHRphZj","name":"Cigarettes After Sex","type":"artist","uri":"spotify:artist:1QAJqy2dA3ihHBFIHRphZj"}],"available_markets":[],"disc_number":1,"duration_ms":286293,"episode":false,"explicit":false,"external_ids":{"isrc":"TCACJ1593857"},"external_urls":{"spotify":"https://open.spotify.com/track/5RROFztQ7ua0p9ttJ0U8nv"},"href":"https://api.spotify.com/v1/tracks/5RROFztQ7ua0p9ttJ0U8nv","id":"5RROFztQ7ua0p9ttJ0U8nv","is_local":false,"name":"Nothing's Gonna Hurt You Baby","popularity":2,"preview_url":null,"track":true,"track_number":1,"type":"track","uri":"spotify:track:5RROFztQ7ua0p9ttJ0U8nv"},"video_thumbnail":{"url":null}},{"added_at":"2016-04-21T13:21:17Z","added_by":{"external_urls":{"spotify":"https://open.spotify.com/user/1162685727"},"href":"https://api.spotify.com/v1/users/1162685727","id":"1162685727","type":"user","uri":"spotify:user:1162685727"},"is_local":false,"primary_color":null,"track":{"album":{"album_type":"album","artists":[{"external_urls":{"spotify":"https://open.spotify.com/artist/0IB0VjX9NSrGX6PjCXGVcq"},"href":"https://api.spotify.com/v1/artists/0IB0VjX9NSrGX6PjCXGVcq","id":"0IB0VjX9NSrGX6PjCXGVcq","name":"Raleigh Ritchie","type":"artist","uri":"spotify:artist:0IB0VjX9NSrGX6PjCXGVcq"}],"available_markets":["AD","AE","AR","AT","AU","BE","BG","BH","BO","BR","CA","CH","CL","CO","CR","CY","CZ","DE","DK","DO","DZ","EC","EE","EG","ES","FI","FR","GB","GR","GT","HK","HN","HU","ID","IE","IL","IS","IT","JO","JP","KW","LB","LI","LT","LU","LV","MA","MC","MT","MX","MY","NI","NL","NO","NZ","OM","PA","PE","PH","PL","PS","PT","PY","QA","RO","SA","SE","SG","SK","SV","TH","TN","TR","TW","US","UY","VN","ZA"],"external_urls":{"spotify":"https://open.spotify.com/album/50EXi4hlRIPF7fLQcWCXyp"},"href":"https://api.spotify.com/v1/albums/50EXi4hlRIPF7fLQcWCXyp","id":"50EXi4hlRIPF7fLQcWCXyp","images":[{"height":640,"url":"https://i.scdn.co/image/ab67616d0000b2733c661c1204b2fa506a9044c1","width":640},{"height":300,"url":"https://i.scdn.co/image/ab67616d00001e023c661c1204b2fa506a9044c1","width":300},{"height":64,"url":"https://i.scdn.co/image/ab67616d000048513c661c1204b2fa506a9044c1","width":64}],"name":"You're a Man Now, Boy (Deluxe)","release_date":"2016-02-26","release_date_precision":"day","total_tracks":18,"type":"album","uri":"spotify:album:50EXi4hlRIPF7fLQcWCXyp"},"artists":[{"external_urls":{"spotify":"https://open.spotify.com/artist/0IB0VjX9NSrGX6PjCXGVcq"},"href":"https://api.spotify.com/v1/artists/0IB0VjX9NSrGX6PjCXGVcq","id":"0IB0VjX9NSrGX6PjCXGVcq","name":"Raleigh Ritchie","type":"artist","uri":"spotify:artist:0IB0VjX9NSrGX6PjCXGVcq"}],"available_markets":["AD","AE","AR","AT","AU","BE","BG","BH","BO","BR","CA","CH","CL","CO","CR","CY","CZ","DE","DK","DO","DZ","EC","EE","EG","ES","FI","FR","GB","GR","GT","HK","HN","HU","ID","IE","IL","IS","IT","JO","JP","KW","LB","LI","LT","LU","LV","MA","MC","MT","MX","MY","NI","NL","NO","NZ","OM","PA","PE","PH","PL","PS","PT","PY","QA","RO","SA","SE","SG","SK","SV","TH","TN","TR","TW","US","UY","VN","ZA"],"disc_number":1,"duration_ms":199586,"episode":false,"explicit":false,"external_ids":{"isrc":"GBARL1501223"},"external_urls":{"spotify":"https://open.spotify.com/track/421lWmPkOiHJhTIMDLxKjP"},"href":"https://api.spotify.com/v1/tracks/421lWmPkOiHJhTIMDLxKjP","id":"421lWmPkOiHJhTIMDLxKjP","is_local":false,"name":"The Last Romance","popularity":34,"preview_url":"https://p.scdn.co/mp3-preview/b02e95fc56d4732b246d9c5f4d6b17c320b37c6c?cid=9950ac751e34487dbbe027c4fd7f8e99","track":true,"track_number":12,"type":"track","uri":"spotify:track:421lWmPkOiHJhTIMDLxKjP"},"video_thumbnail":{"url":null}},{"added_at":"2016-04-21T13:21:42Z","added_by":{"external_urls":{"spotify":"https://open.spotify.com/user/1162685727"},"href":"https://api.spotify.com/v1/users/1162685727","id":"1162685727","type":"user","uri":"spotify:user:1162685727"},"is_local":false,"primary_color":null,"track":{"album":{"album_type":"album","artists":[{"external_urls":{"spotify":"https://open.spotify.com/artist/6olWbKW2VLhFCHfOi0iEDb"},"href":"https://api.spotify.com/v1/artists/6olWbKW2VLhFCHfOi0iEDb","id":"6olWbKW2VLhFCHfOi0iEDb","name":"Hudson Mohawke","type":"artist","uri":"spotify:artist:6olWbKW2VLhFCHfOi0iEDb"}],"available_markets":["AD","AE","AR","AT","AU","BE","BG","BH","BO","BR","CA","CH","CL","CO","CR","CY","CZ","DE","DK","DO","DZ","EC","EE","EG","ES","FI","FR","GB","GR","GT","HK","HN","HU","ID","IE","IL","IN","IS","IT","JO","JP","KW","LB","LI","LT","LU","LV","MA","MC","MT","MX","MY","NI","NL","NO","NZ","OM","PA","PE","PH","PL","PS","PT","PY","QA","RO","SA","SE","SG","SK","SV","TH","TN","TR","TW","US","UY","VN","ZA"],"external_urls":{"spotify":"https://open.spotify.com/album/77ssrzSiIdGl7zaKn3oFx0"},"href":"https://api.spotify.com/v1/albums/77ssrzSiIdGl7zaKn3oFx0","id":"77ssrzSiIdGl7zaKn3oFx0","images":[{"height":640,"url":"https://i.scdn.co/image/ab67616d0000b2737988db4ed88e7d50f8b634cb","width":640},{"height":300,"url":"https://i.scdn.co/image/ab67616d00001e027988db4ed88e7d50f8b634cb","width":300},{"height":64,"url":"https://i.scdn.co/image/ab67616d000048517988db4ed88e7d50f8b634cb","width":64}],"name":"Lantern","release_date":"2015-06-15","release_date_precision":"day","total_tracks":14,"type":"album","uri":"spotify:album:77ssrzSiIdGl7zaKn3oFx0"},"artists":[{"external_urls":{"spotify":"https://open.spotify.com/artist/6olWbKW2VLhFCHfOi0iEDb"},"href":"https://api.spotify.com/v1/artists/6olWbKW2VLhFCHfOi0iEDb","id":"6olWbKW2VLhFCHfOi0iEDb","name":"Hudson Mohawke","type":"artist","uri":"spotify:artist:6olWbKW2VLhFCHfOi0iEDb"},{"external_urls":{"spotify":"https://open.spotify.com/artist/3koJmQqTa9Eh7oy4y1XaZU"},"href":"https://api.spotify.com/v1/artists/3koJmQqTa9Eh7oy4y1XaZU","id":"3koJmQqTa9Eh7oy4y1XaZU","name":"Antony","type":"artist","uri":"spotify:artist:3koJmQqTa9Eh7oy4y1XaZU"}],"available_markets":["AD","AE","AR","AT","AU","BE","BG","BH","BO","BR","CA","CH","CL","CO","CR","CY","CZ","DE","DK","DO","DZ","EC","EE","EG","ES","FI","FR","GB","GR","GT","HK","HN","HU","ID","IE","IL","IN","IS","IT","JO","JP","KW","LB","LI","LT","LU","LV","MA","MC","MT","MX","MY","NI","NL","NO","NZ","OM","PA","PE","PH","PL","PS","PT","PY","QA","RO","SA","SE","SG","SK","SV","TH","TN","TR","TW","US","UY","VN","ZA"],"disc_number":1,"duration_ms":276066,"episode":false,"explicit":false,"external_ids":{"isrc":"GBBPW1500028"},"external_urls":{"spotify":"https://open.spotify.com/track/4gqW3WQrkOs6MlFHX9shUR"},"href":"https://api.spotify.com/v1/tracks/4gqW3WQrkOs6MlFHX9shUR","id":"4gqW3WQrkOs6MlFHX9shUR","is_local":false,"name":"Indian Steps","popularity":21,"preview_url":"https://p.scdn.co/mp3-preview/d36e580fb7074d46543f407919f37369160991d0?cid=9950ac751e34487dbbe027c4fd7f8e99","track":true,"track_number":7,"type":"track","uri":"spotify:track:4gqW3WQrkOs6MlFHX9shUR"},"video_thumbnail":{"url":null}},{"added_at":"2016-04-25T15:01:07Z","added_by":{"external_urls":{"spotify":"https://open.spotify.com/user/1162685727"},"href":"https://api.spotify.com/v1/users/1162685727","id":"1162685727","type":"user","uri":"spotify:user:1162685727"},"is_local":false,"primary_color":null,"track":{"album":{"album_type":"album","artists":[{"external_urls":{"spotify":"https://open.spotify.com/artist/5hokuav35Jh2qn4RKDDBkL"},"href":"https://api.spotify.com/v1/artists/5hokuav35Jh2qn4RKDDBkL","id":"5hokuav35Jh2qn4RKDDBkL","name":"HeCTA","type":"artist","uri":"spotify:artist:5hokuav35Jh2qn4RKDDBkL"}],"available_markets":[],"external_urls":{"spotify":"https://open.spotify.com/album/1aDGGp3yd6loVBLTt24byA"},"href":"https://api.spotify.com/v1/albums/1aDGGp3yd6loVBLTt24byA","id":"1aDGGp3yd6loVBLTt24byA","images":[{"height":640,"url":"https://i.scdn.co/image/ab67616d0000b2734867cf1d8dec4e6e8e7e7f3a","width":640},{"height":300,"url":"https://i.scdn.co/image/ab67616d00001e024867cf1d8dec4e6e8e7e7f3a","width":300},{"height":64,"url":"https://i.scdn.co/image/ab67616d000048514867cf1d8dec4e6e8e7e7f3a","width":64}],"name":"The Diet","release_date":"2015-09-18","release_date_precision":"day","total_tracks":9,"type":"album","uri":"spotify:album:1aDGGp3yd6loVBLTt24byA"},"artists":[{"external_urls":{"spotify":"https://open.spotify.com/artist/5hokuav35Jh2qn4RKDDBkL"},"href":"https://api.spotify.com/v1/artists/5hokuav35Jh2qn4RKDDBkL","id":"5hokuav35Jh2qn4RKDDBkL","name":"HeCTA","type":"artist","uri":"spotify:artist:5hokuav35Jh2qn4RKDDBkL"}],"available_markets":[],"disc_number":1,"duration_ms":331253,"episode":false,"explicit":false,"external_ids":{"isrc":"DED621501206"},"external_urls":{"spotify":"https://open.spotify.com/track/3MdwbFYCFqpuR7YToEMRji"},"href":"https://api.spotify.com/v1/tracks/3MdwbFYCFqpuR7YToEMRji","id":"3MdwbFYCFqpuR7YToEMRji","is_local":false,"name":"Sympathy For The Auto Industry","popularity":0,"preview_url":null,"track":true,"track_number":2,"type":"track","uri":"spotify:track:3MdwbFYCFqpuR7YToEMRji"},"video_thumbnail":{"url":null}},{"added_at":"2016-04-27T14:23:24Z","added_by":{"external_urls":{"spotify":"https://open.spotify.com/user/1162685727"},"href":"https://api.spotify.com/v1/users/1162685727","id":"1162685727","type":"user","uri":"spotify:user:1162685727"},"is_local":false,"primary_color":null,"track":{"album":{"album_type":"album","artists":[{"external_urls":{"spotify":"https://open.spotify.com/artist/73LvjicByRK5LazcQYZMAY"},"href":"https://api.spotify.com/v1/artists/73LvjicByRK5LazcQYZMAY","id":"73LvjicByRK5LazcQYZMAY","name":"Blanck Mass","type":"artist","uri":"spotify:artist:73LvjicByRK5LazcQYZMAY"}],"available_markets":[],"external_urls":{"spotify":"https://open.spotify.com/album/1KZFsO5kth2c0xMPyL7rSx"},"href":"https://api.spotify.com/v1/albums/1KZFsO5kth2c0xMPyL7rSx","id":"1KZFsO5kth2c0xMPyL7rSx","images":[{"height":640,"url":"https://i.scdn.co/image/ab67616d0000b2736f8035e05f0a7c8f273195b8","width":640},{"height":300,"url":"https://i.scdn.co/image/ab67616d00001e026f8035e05f0a7c8f273195b8","width":300},{"height":64,"url":"https://i.scdn.co/image/ab67616d000048516f8035e05f0a7c8f273195b8","width":64}],"name":"Dumb Flesh","release_date":"2015-05-12","release_date_precision":"day","total_tracks":8,"type":"album","uri":"spotify:album:1KZFsO5kth2c0xMPyL7rSx"},"artists":[{"external_urls":{"spotify":"https://open.spotify.com/artist/73LvjicByRK5LazcQYZMAY"},"href":"https://api.spotify.com/v1/artists/73LvjicByRK5LazcQYZMAY","id":"73LvjicByRK5LazcQYZMAY","name":"Blanck Mass","type":"artist","uri":"spotify:artist:73LvjicByRK5LazcQYZMAY"}],"available_markets":[],"disc_number":1,"duration_ms":306733,"episode":false,"explicit":false,"external_ids":{"isrc":"US5NR1513604"},"external_urls":{"spotify":"https://open.spotify.com/track/4hwucfOrP2d62YYIFN3HMn"},"href":"https://api.spotify.com/v1/tracks/4hwucfOrP2d62YYIFN3HMn","id":"4hwucfOrP2d62YYIFN3HMn","is_local":false,"name":"Atrophies","popularity":0,"preview_url":null,"track":true,"track_number":4,"type":"track","uri":"spotify:track:4hwucfOrP2d62YYIFN3HMn"},"video_thumbnail":{"url":null}}],"limit":100,"next":null,"offset":0,"previous":null,"total":5}]