{
	"name": "September Top 5 2016",
	"month": "september",
	"year": "2016",
	"id": "5JhwyhOfjNbjggvxmiJZE0",
	"tracks": [
		{
			"album": {
				"name": "One By One",
				"year": "",
				"id": "",
				"externalId": {
					"spotify": "2TIp2qGorHvqyaiAb82Awe"
				}
			},
			"artists": [
				{
					"name": "Foo Fighters",
					"id": "",
					"externalId": {
						"spotify": "7jy3rLJdDQY21OgRLCZ9sD"
					}
				}
			],
			"name": "Low",
			"id": "",
			"length": 268040,
			"externalId": {
				"spotify": "01ERgmlDJjGYFXkBLgRTFp"
			}
		},
		{
			"album": {
				"name": "Good Times",
				"year": "",
				"id": "",
				"externalId": {
					"spotify": "36pKx43hkeUF1OGxuxKkZw"
				}
			},
			"artists": [
				{
					"name": "Willie Nelson",
					"id": "",
					"externalId": {
						"spotify": "5W5bDNCqJ1jbCgTxDD0Cb3"
					}
				}
			],
			"name": "Buddy",
			"id": "",
			"length": 135973,
			"externalId": {
				"spotify": "1dbQNSAXlOEtngcIZAOfPO"
			}
		},
		{
			"album": {
				"name": "Shadows in the Night",
				"year": "",
				"id": "",
				"externalId": {
					"spotify": "2mVpSZrllFAWhOgCoyz8ow"
				}
			},
			"artists": [
				{
					"name": "Bob Dylan",
					"id": "",
					"externalId": {
						"spotify": "74ASZWbe4lXaubB36ztrGX"
					}
				}
			],
			"name": "What'll I Do",
			"id": "",
			"length": 195786,
			"externalId": {
				"spotify": "5pWyOsWnOrSfDzNqCqBzOY"
			}
		},
		{
			"album": {
				"name": "Elsewhere Anchises",
				"year": "",
				"id": "",
				"externalId": {
					"spotify": "24i8Sj6loL2qIJNsrojnGT"
				}
			},
			"artists": [
				{
					"name": "David Holmes",
					"id": "",
					"externalId": {
						"spotify": "10kGEgP8MxhlfeA2tMinsL"
					}
				},
				{
					"name": "Jon Hopkins",
					"id": "",
					"externalId": {
						"spotify": "7yxi31szvlbwvKq9dYOmFI"
					}
				},
				{
					"name": "Stephen Rea",
					"id": "",
					"externalId": {
						"spotify": "5KIabrrmudYdwnxbEl0pOZ"
					}
				}
			],
			"name": "Elsewhere Anchises",
			"id": "",
			"length": 290769,
			"externalId": {
				"spotify": "4nezbRPMpvIWObOOBnOmXk"
			}
		},
		{
			"album": {
				"name": "Avalon",
				"year": "",
				"id": "",
				"externalId": {
					"spotify": "3JXODSjT9mUz2lIb4YIErw"
				}
			},
			"artists": [
				{
					"name": "Roxy Music",
					"id": "",
					"externalId": {
						"spotify": "3fhOTtm0LBJ3Ojn4hIljLo"
					}
				}
			],
			"name": "More Than This",
			"id": "",
			"length": 270693,
			"externalId": {
				"spotify": "6N7gPTru90HYLRUIVDQ185"
			}
		}
	]
}