{
	"name": "January Top 5 2012",
	"month": "january",
	"year": "2012",
	"id": "5y5StyxUfdoGpMjD2GNe46",
	"tracks": [
		{
			"album": {
				"name": "Save the World, Get the Girl",
				"year": "",
				"id": "cd88e6a6-59f5-47bd-b740-be75f566d622",
				"externalId": {
					"spotify": null
				}
			},
			"artists": [
				{
					"name": "The King Blues",
					"id": "cfdb3c95-787a-4da9-845e-1226e290e0cf",
					"externalId": {
						"spotify": null
					}
				}
			],
			"name": "What If Punk Never Happened (Dan Le Sac vs. Scroobius Pip Remix)",
			"id": "29f61e4d-e946-43ac-9e8b-b089d56d5114",
			"length": 539000,
			"externalId": {
				"spotify": null
			}
		},
		{
			"album": {
				"name": "Black Celebration",
				"year": "",
				"id": "01bfac66-445d-4f14-8717-0cb657ad6e00",
				"externalId": {
					"spotify": null
				}
			},
			"artists": [
				{
					"name": "Depeche Mode",
					"id": "",
					"externalId": {
						"spotify": null
					}
				}
			],
			"name": "Stripped",
			"id": "744c1430-2840-48cc-ad0b-4cbb346177a7",
			"length": 231000,
			"externalId": {
				"spotify": null
			}
		},
		{
			"album": {
				"name": "BRONZE",
				"year": "",
				"id": "870e94fc-70f6-4cb8-b610-20e6efdff3d6",
				"externalId": {
					"spotify": null
				}
			},
			"artists": [
				{
					"name": "BRONZE",
					"id": "d0951720-7172-45c1-86b7-039a60a0eae2",
					"externalId": {
						"spotify": null
					}
				}
			],
			"name": "Sunny Day",
			"id": "aea82e17-3a08-42d6-8eb2-c15f1ad1f10d",
			"length": 333000,
			"externalId": {
				"spotify": null
			}
		},
		{
			"album": {
				"name": "The Head On The Door",
				"year": "",
				"id": "a8d44881-d288-42e3-92e1-8545a743de3e",
				"externalId": {
					"spotify": null
				}
			},
			"artists": [
				{
					"name": "The Cure",
					"id": "158c2ac3-0439-4af4-ae98-e027d2c8e1af",
					"externalId": {
						"spotify": null
					}
				}
			],
			"name": "Close To Me",
			"id": "514f51aa-1a75-4650-8450-76a1f4fbca7c",
			"length": 204000,
			"externalId": {
				"spotify": null
			}
		},
		{
			"album": {
				"name": "Bamnan and Slivercork",
				"year": "",
				"id": "8b130a3e-e967-4d25-a77c-e4c0b3f9bf82",
				"externalId": {
					"spotify": null
				}
			},
			"artists": [
				{
					"name": "Midlake",
					"id": "e05ff430-a473-449d-81b0-891f2c41ed6a",
					"externalId": {
						"spotify": null
					}
				}
			],
			"name": "Kingfish Pies",
			"id": "2b9591ee-dc01-4596-ab0b-897d1e40f261",
			"length": 260000,
			"externalId": {
				"spotify": null
			}
		}
	]
}