{
	"name": "March Top 5 2011",
	"month": "march",
	"year": "2011",
	"id": "068WslXVXKRCjbFVAADLrR",
	"tracks": [
		{
			"album": {
				"name": "The King Of Limbs",
				"year": "",
				"id": "",
				"externalId": {
					"spotify": null
				}
			},
			"artists": [
				{
					"name": "Radiohead",
					"id": "",
					"externalId": {
						"spotify": null
					}
				}
			],
			"name": "Codex",
			"id": "",
			"length": 286000,
			"externalId": {
				"spotify": null
			}
		},
		{
			"album": {
				"name": "High Violet",
				"year": "",
				"id": "",
				"externalId": {
					"spotify": null
				}
			},
			"artists": [
				{
					"name": "The National",
					"id": "",
					"externalId": {
						"spotify": null
					}
				}
			],
			"name": "Conversation 16",
			"id": "",
			"length": 259000,
			"externalId": {
				"spotify": null
			}
		},
		{
			"album": {
				"name": "Body Talk",
				"year": "",
				"id": "",
				"externalId": {
					"spotify": null
				}
			},
			"artists": [
				{
					"name": "Robyn",
					"id": "",
					"externalId": {
						"spotify": null
					}
				}
			],
			"name": "U Should Know Better",
			"id": "",
			"length": 241000,
			"externalId": {
				"spotify": null
			}
		},
		{
			"album": {
				"name": "Magic Chairs",
				"year": "",
				"id": "",
				"externalId": {
					"spotify": null
				}
			},
			"artists": [
				{
					"name": "Efterklang",
					"id": "",
					"externalId": {
						"spotify": null
					}
				}
			],
			"name": "Raincoats",
			"id": "",
			"length": 260000,
			"externalId": {
				"spotify": null
			}
		},
		{
			"album": {
				"name": "Kiss Each Other Clean",
				"year": "",
				"id": "",
				"externalId": {
					"spotify": null
				}
			},
			"artists": [
				{
					"name": "Iron & Wine",
					"id": "",
					"externalId": {
						"spotify": null
					}
				}
			],
			"name": "Rabbit Will Run",
			"id": "",
			"length": 331000,
			"externalId": {
				"spotify": null
			}
		}
	]
}