﻿[{"href":"https://api.spotify.com/v1/playlists/0Y1DbY1eQHg8qhtSeHKtu2/tracks?offset=0&limit=100","items":[{"added_at":"2019-07-04T08:01:56Z","added_by":{"external_urls":{"spotify":"https://open.spotify.com/user/1162685727"},"href":"https://api.spotify.com/v1/users/1162685727","id":"1162685727","type":"user","uri":"spotify:user:1162685727"},"is_local":false,"primary_color":null,"track":{"album":{"album_type":"album","artists":[{"external_urls":{"spotify":"https://open.spotify.com/artist/4CvTDPKA6W06DRfBnZKrau"},"href":"https://api.spotify.com/v1/artists/4CvTDPKA6W06DRfBnZKrau","id":"4CvTDPKA6W06DRfBnZKrau","name":"Thom Yorke","type":"artist","uri":"spotify:artist:4CvTDPKA6W06DRfBnZKrau"}],"available_markets":["AD","AE","AT","AU","BE","BG","BH","CH","CY","CZ","DE","DK","DZ","EE","EG","ES","FI","FR","GB","GR","HK","HU","ID","IE","IL","IN","IS","IT","JO","JP","KW","LB","LI","LT","LU","LV","MA","MC","MT","MY","NI","NL","NO","NZ","OM","PH","PL","PS","PT","QA","RO","SA","SE","SG","SK","TH","TN","TR","TW","VN","ZA"],"external_urls":{"spotify":"https://open.spotify.com/album/5a4VSyY7zsfVVqHweYHG7R"},"href":"https://api.spotify.com/v1/albums/5a4VSyY7zsfVVqHweYHG7R","id":"5a4VSyY7zsfVVqHweYHG7R","images":[{"height":640,"url":"https://i.scdn.co/image/ab67616d0000b273bfcd8d6b28c07d92a902e1c2","width":640},{"height":300,"url":"https://i.scdn.co/image/ab67616d00001e02bfcd8d6b28c07d92a902e1c2","width":300},{"height":64,"url":"https://i.scdn.co/image/ab67616d00004851bfcd8d6b28c07d92a902e1c2","width":64}],"name":"ANIMA","release_date":"2019-06-26","release_date_precision":"day","total_tracks":9,"type":"album","uri":"spotify:album:5a4VSyY7zsfVVqHweYHG7R"},"artists":[{"external_urls":{"spotify":"https://open.spotify.com/artist/4CvTDPKA6W06DRfBnZKrau"},"href":"https://api.spotify.com/v1/artists/4CvTDPKA6W06DRfBnZKrau","id":"4CvTDPKA6W06DRfBnZKrau","name":"Thom Yorke","type":"artist","uri":"spotify:artist:4CvTDPKA6W06DRfBnZKrau"}],"available_markets":["AD","AE","AT","AU","BE","BG","BH","CH","CY","CZ","DE","DK","DZ","EE","EG","ES","FI","FR","GB","GR","HK","HU","ID","IE","IL","IN","IS","IT","JO","JP","KW","LB","LI","LT","LU","LV","MA","MC","MT","MY","NI","NL","NO","NZ","OM","PH","PL","PS","PT","QA","RO","SA","SE","SG","SK","TH","TN","TR","TW","VN","ZA"],"disc_number":1,"duration_ms":323080,"episode":false,"explicit":false,"external_ids":{"isrc":"GB4YG1900213"},"external_urls":{"spotify":"https://open.spotify.com/track/0F4EoaMJmWNz8vS8tKgsqY"},"href":"https://api.spotify.com/v1/tracks/0F4EoaMJmWNz8vS8tKgsqY","id":"0F4EoaMJmWNz8vS8tKgsqY","is_local":false,"name":"Dawn Chorus","popularity":54,"preview_url":"https://p.scdn.co/mp3-preview/d25e845dd4a633e9c4ee094e2b47e887b3c80a44?cid=9950ac751e34487dbbe027c4fd7f8e99","track":true,"track_number":4,"type":"track","uri":"spotify:track:0F4EoaMJmWNz8vS8tKgsqY"},"video_thumbnail":{"url":null}},{"added_at":"2019-07-15T08:17:35Z","added_by":{"external_urls":{"spotify":"https://open.spotify.com/user/1162685727"},"href":"https://api.spotify.com/v1/users/1162685727","id":"1162685727","type":"user","uri":"spotify:user:1162685727"},"is_local":false,"primary_color":null,"track":{"album":{"album_type":"single","artists":[{"external_urls":{"spotify":"https://open.spotify.com/artist/2WoVwexZuODvclzULjPQtm"},"href":"https://api.spotify.com/v1/artists/2WoVwexZuODvclzULjPQtm","id":"2WoVwexZuODvclzULjPQtm","name":"Sampha","type":"artist","uri":"spotify:artist:2WoVwexZuODvclzULjPQtm"}],"available_markets":[],"external_urls":{"spotify":"https://open.spotify.com/album/0vrEKuIGhomsOTY2n7ChA1"},"href":"https://api.spotify.com/v1/albums/0vrEKuIGhomsOTY2n7ChA1","id":"0vrEKuIGhomsOTY2n7ChA1","images":[{"height":640,"url":"https://i.scdn.co/image/ab67616d0000b2735937828f856b0a221ae30d69","width":640},{"height":300,"url":"https://i.scdn.co/image/ab67616d00001e025937828f856b0a221ae30d69","width":300},{"height":64,"url":"https://i.scdn.co/image/ab67616d000048515937828f856b0a221ae30d69","width":64}],"name":"Dual","release_date":"2013-07-29","release_date_precision":"day","total_tracks":6,"type":"album","uri":"spotify:album:0vrEKuIGhomsOTY2n7ChA1"},"artists":[{"external_urls":{"spotify":"https://open.spotify.com/artist/2WoVwexZuODvclzULjPQtm"},"href":"https://api.spotify.com/v1/artists/2WoVwexZuODvclzULjPQtm","id":"2WoVwexZuODvclzULjPQtm","name":"Sampha","type":"artist","uri":"spotify:artist:2WoVwexZuODvclzULjPQtm"}],"available_markets":[],"disc_number":1,"duration_ms":226380,"episode":false,"explicit":false,"external_ids":{"isrc":"GB6HK1300074"},"external_urls":{"spotify":"https://open.spotify.com/track/5SGNqhwXguf8tUnnO7METu"},"href":"https://api.spotify.com/v1/tracks/5SGNqhwXguf8tUnnO7METu","id":"5SGNqhwXguf8tUnnO7METu","is_local":false,"name":"Without","popularity":0,"preview_url":null,"track":true,"track_number":3,"type":"track","uri":"spotify:track:5SGNqhwXguf8tUnnO7METu"},"video_thumbnail":{"url":null}},{"added_at":"2019-07-04T08:02:18Z","added_by":{"external_urls":{"spotify":"https://open.spotify.com/user/1162685727"},"href":"https://api.spotify.com/v1/users/1162685727","id":"1162685727","type":"user","uri":"spotify:user:1162685727"},"is_local":false,"primary_color":null,"track":{"album":{"album_type":"album","artists":[{"external_urls":{"spotify":"https://open.spotify.com/artist/5a2EaR3hamoenG9rDuVn8j"},"href":"https://api.spotify.com/v1/artists/5a2EaR3hamoenG9rDuVn8j","id":"5a2EaR3hamoenG9rDuVn8j","name":"Prince","type":"artist","uri":"spotify:artist:5a2EaR3hamoenG9rDuVn8j"}],"available_markets":["AD","AE","AR","AT","AU","BE","BG","BH","BO","BR","CA","CH","CL","CO","CR","CY","CZ","DE","DK","DO","DZ","EC","EE","EG","ES","FI","FR","GB","GR","GT","HK","HN","HU","ID","IE","IL","IS","IT","JO","JP","KW","LB","LI","LT","LU","LV","MA","MC","MT","MX","MY","NI","NL","NO","NZ","OM","PA","PE","PH","PL","PT","PY","QA","RO","SA","SE","SG","SK","SV","TH","TN","TR","TW","US","UY","VN","ZA"],"external_urls":{"spotify":"https://open.spotify.com/album/7nXJ5k4XgRj5OLg9m8V3zc"},"href":"https://api.spotify.com/v1/albums/7nXJ5k4XgRj5OLg9m8V3zc","id":"7nXJ5k4XgRj5OLg9m8V3zc","images":[{"height":640,"url":"https://i.scdn.co/image/ab67616d0000b273d52bfb90ee8dfeda8378b99b","width":640},{"height":300,"url":"https://i.scdn.co/image/ab67616d00001e02d52bfb90ee8dfeda8378b99b","width":300},{"height":64,"url":"https://i.scdn.co/image/ab67616d00004851d52bfb90ee8dfeda8378b99b","width":64}],"name":"Purple Rain","release_date":"1984-06-25","release_date_precision":"day","total_tracks":9,"type":"album","uri":"spotify:album:7nXJ5k4XgRj5OLg9m8V3zc"},"artists":[{"external_urls":{"spotify":"https://open.spotify.com/artist/5a2EaR3hamoenG9rDuVn8j"},"href":"https://api.spotify.com/v1/artists/5a2EaR3hamoenG9rDuVn8j","id":"5a2EaR3hamoenG9rDuVn8j","name":"Prince","type":"artist","uri":"spotify:artist:5a2EaR3hamoenG9rDuVn8j"}],"available_markets":["AD","AE","AR","AT","AU","BE","BG","BH","BO","BR","CA","CH","CL","CO","CR","CY","CZ","DE","DK","DO","DZ","EC","EE","EG","ES","FI","FR","GB","GR","GT","HK","HN","HU","ID","IE","IL","IS","IT","JO","JP","KW","LB","LI","LT","LU","LV","MA","MC","MT","MX","MY","NI","NL","NO","NZ","OM","PA","PE","PH","PL","PT","PY","QA","RO","SA","SE","SG","SK","SV","TH","TN","TR","TW","US","UY","VN","ZA"],"disc_number":1,"duration_ms":178986,"episode":false,"explicit":false,"external_ids":{"isrc":"USWB10001878"},"external_urls":{"spotify":"https://open.spotify.com/track/6fBwVe6udYdnRqwqo06if8"},"href":"https://api.spotify.com/v1/tracks/6fBwVe6udYdnRqwqo06if8","id":"6fBwVe6udYdnRqwqo06if8","is_local":false,"name":"I Would Die 4 U","popularity":59,"preview_url":"https://p.scdn.co/mp3-preview/395d416c1d2bc452c4326513cc2ca46f572cb836?cid=9950ac751e34487dbbe027c4fd7f8e99","track":true,"track_number":7,"type":"track","uri":"spotify:track:6fBwVe6udYdnRqwqo06if8"},"video_thumbnail":{"url":null}},{"added_at":"2019-07-04T08:01:58Z","added_by":{"external_urls":{"spotify":"https://open.spotify.com/user/1162685727"},"href":"https://api.spotify.com/v1/users/1162685727","id":"1162685727","type":"user","uri":"spotify:user:1162685727"},"is_local":false,"primary_color":null,"track":{"album":{"album_type":"single","artists":[{"external_urls":{"spotify":"https://open.spotify.com/artist/63vaeIIBKIe9zT91EORVbr"},"href":"https://api.spotify.com/v1/artists/63vaeIIBKIe9zT91EORVbr","id":"63vaeIIBKIe9zT91EORVbr","name":"MorMor","type":"artist","uri":"spotify:artist:63vaeIIBKIe9zT91EORVbr"}],"available_markets":["AD","AE","AR","AT","AU","BE","BG","BH","BO","BR","CA","CH","CL","CO","CR","CY","CZ","DE","DK","DO","DZ","EC","EE","EG","ES","FI","FR","GB","GR","GT","HK","HN","HU","ID","IE","IL","IN","IS","IT","JO","JP","KW","LB","LI","LT","LU","LV","MA","MC","MT","MX","MY","NI","NL","NO","NZ","OM","PA","PE","PH","PL","PS","PT","PY","QA","RO","SA","SE","SG","SK","SV","TH","TN","TR","TW","US","UY","VN","ZA"],"external_urls":{"spotify":"https://open.spotify.com/album/7G6KMFNhuWlwwn4zGZTmk9"},"href":"https://api.spotify.com/v1/albums/7G6KMFNhuWlwwn4zGZTmk9","id":"7G6KMFNhuWlwwn4zGZTmk9","images":[{"height":640,"url":"https://i.scdn.co/image/ab67616d0000b273c0c3ea2b63b251637f0f155a","width":640},{"height":300,"url":"https://i.scdn.co/image/ab67616d00001e02c0c3ea2b63b251637f0f155a","width":300},{"height":64,"url":"https://i.scdn.co/image/ab67616d00004851c0c3ea2b63b251637f0f155a","width":64}],"name":"Some Place Else","release_date":"2019-05-03","release_date_precision":"day","total_tracks":6,"type":"album","uri":"spotify:album:7G6KMFNhuWlwwn4zGZTmk9"},"artists":[{"external_urls":{"spotify":"https://open.spotify.com/artist/63vaeIIBKIe9zT91EORVbr"},"href":"https://api.spotify.com/v1/artists/63vaeIIBKIe9zT91EORVbr","id":"63vaeIIBKIe9zT91EORVbr","name":"MorMor","type":"artist","uri":"spotify:artist:63vaeIIBKIe9zT91EORVbr"}],"available_markets":["AD","AE","AR","AT","AU","BE","BG","BH","BO","BR","CA","CH","CL","CO","CR","CY","CZ","DE","DK","DO","DZ","EC","EE","EG","ES","FI","FR","GB","GR","GT","HK","HN","HU","ID","IE","IL","IN","IS","IT","JO","JP","KW","LB","LI","LT","LU","LV","MA","MC","MT","MX","MY","NI","NL","NO","NZ","OM","PA","PE","PH","PL","PS","PT","PY","QA","RO","SA","SE","SG","SK","SV","TH","TN","TR","TW","US","UY","VN","ZA"],"disc_number":1,"duration_ms":214885,"episode":false,"explicit":false,"external_ids":{"isrc":"GBKPL1947869"},"external_urls":{"spotify":"https://open.spotify.com/track/5Hu24z7izB3LKi6pHaPq3C"},"href":"https://api.spotify.com/v1/tracks/5Hu24z7izB3LKi6pHaPq3C","id":"5Hu24z7izB3LKi6pHaPq3C","is_local":false,"name":"Some Place Else","popularity":54,"preview_url":"https://p.scdn.co/mp3-preview/e64226f327c530740c9ef8e9ba7fc145a40d8f14?cid=9950ac751e34487dbbe027c4fd7f8e99","track":true,"track_number":1,"type":"track","uri":"spotify:track:5Hu24z7izB3LKi6pHaPq3C"},"video_thumbnail":{"url":null}},{"added_at":"2019-07-15T08:17:19Z","added_by":{"external_urls":{"spotify":"https://open.spotify.com/user/1162685727"},"href":"https://api.spotify.com/v1/users/1162685727","id":"1162685727","type":"user","uri":"spotify:user:1162685727"},"is_local":false,"primary_color":null,"track":{"album":{"album_type":"compilation","artists":[{"external_urls":{"spotify":"https://open.spotify.com/artist/0LyfQWJT6nXafLPZqxe9Of"},"href":"https://api.spotify.com/v1/artists/0LyfQWJT6nXafLPZqxe9Of","id":"0LyfQWJT6nXafLPZqxe9Of","name":"Various Artists","type":"artist","uri":"spotify:artist:0LyfQWJT6nXafLPZqxe9Of"}],"available_markets":["AD","AE","AR","AT","AU","BE","BG","BH","BO","BR","CA","CH","CL","CO","CR","CY","CZ","DE","DK","DO","DZ","EC","EE","EG","ES","FI","FR","GB","GR","GT","HK","HN","HU","ID","IE","IL","IN","IS","IT","JO","JP","KW","LB","LI","LT","LU","LV","MA","MC","MT","MX","MY","NI","NL","NO","NZ","OM","PA","PE","PH","PL","PS","PT","PY","QA","RO","SA","SE","SG","SK","SV","TH","TN","TR","TW","US","UY","VN","ZA"],"external_urls":{"spotify":"https://open.spotify.com/album/0CTCk1eshEadFqZ4NBfe9N"},"href":"https://api.spotify.com/v1/albums/0CTCk1eshEadFqZ4NBfe9N","id":"0CTCk1eshEadFqZ4NBfe9N","images":[{"height":640,"url":"https://i.scdn.co/image/ab67616d0000b273bd0db295c0164ddbc0584ebb","width":640},{"height":300,"url":"https://i.scdn.co/image/ab67616d00001e02bd0db295c0164ddbc0584ebb","width":300},{"height":64,"url":"https://i.scdn.co/image/ab67616d00004851bd0db295c0164ddbc0584ebb","width":64}],"name":"Stranger Things (Soundtrack from the Netflix Original Series)","release_date":"2017-10-27","release_date_precision":"day","total_tracks":30,"type":"album","uri":"spotify:album:0CTCk1eshEadFqZ4NBfe9N"},"artists":[{"external_urls":{"spotify":"https://open.spotify.com/artist/7C4sUpWGlTy7IANjruj02I"},"href":"https://api.spotify.com/v1/artists/7C4sUpWGlTy7IANjruj02I","id":"7C4sUpWGlTy7IANjruj02I","name":"Peter Gabriel","type":"artist","uri":"spotify:artist:7C4sUpWGlTy7IANjruj02I"}],"available_markets":["AD","AE","AR","AT","AU","BE","BG","BH","BO","BR","CA","CH","CL","CO","CR","CY","CZ","DE","DK","DO","DZ","EC","EE","EG","ES","FI","FR","GB","GR","GT","HK","HN","HU","ID","IE","IL","IN","IS","IT","JO","JP","KW","LB","LI","LT","LU","LV","MA","MC","MT","MX","MY","NI","NL","NO","NZ","OM","PA","PE","PH","PL","PS","PT","PY","QA","RO","SA","SE","SG","SK","SV","TH","TN","TR","TW","US","UY","VN","ZA"],"disc_number":1,"duration_ms":243266,"episode":false,"explicit":false,"external_ids":{"isrc":"GBCPB0900622"},"external_urls":{"spotify":"https://open.spotify.com/track/2Os83Fjr9ixsIRLMiaGCnj"},"href":"https://api.spotify.com/v1/tracks/2Os83Fjr9ixsIRLMiaGCnj","id":"2Os83Fjr9ixsIRLMiaGCnj","is_local":false,"name":"Heroes","popularity":55,"preview_url":"https://p.scdn.co/mp3-preview/b27e409c3e62ffe203f6218baa5e4ce6a2d965d7?cid=9950ac751e34487dbbe027c4fd7f8e99","track":true,"track_number":27,"type":"track","uri":"spotify:track:2Os83Fjr9ixsIRLMiaGCnj"},"video_thumbnail":{"url":null}}],"limit":100,"next":null,"offset":0,"previous":null,"total":5}]